boardfarm3/__init__.py
boardfarm3/exceptions.py
boardfarm3/main.py
boardfarm3/py.typed
boardfarm3/configs/__init__.py
boardfarm3/configs/boardfarm_config_example.json
boardfarm3/configs/boardfarm_env_example.json
boardfarm3/configs/boardfarm_env_rpi4rdkb_example.json
boardfarm3/configs/boardfarm_inventory_schema.json
boardfarm3/configs/boardfarm_rpi4rdkb_config_example.json
boardfarm3/configs/kea_eth_provisioner4.conf
boardfarm3/configs/kea_eth_provisioner6.conf
boardfarm3/configs/logging.json
boardfarm3/configs/mibs/BRIDGE-MIB.mib
boardfarm3/configs/mibs/ENTITY-MIB.mib
boardfarm3/configs/mibs/ENTITY-SENSOR-MIB.mib
boardfarm3/configs/mibs/EtherLike-MIB.mib
boardfarm3/configs/mibs/HCNUM-TC.mib
boardfarm3/configs/mibs/IANA-ENTITY-MIB.mib
boardfarm3/configs/mibs/IANA-RTPROTO-MIB.txt
boardfarm3/configs/mibs/IF-MIB.mib
boardfarm3/configs/mibs/IGMP-STD-MIB.mib
boardfarm3/configs/mibs/INET-ADDRESS-MIB.mib
boardfarm3/configs/mibs/INTEGRATED-SERVICES-MIB.mib
boardfarm3/configs/mibs/IP-FORWARD-MIB.mib
boardfarm3/configs/mibs/IP-MIB.mib
boardfarm3/configs/mibs/IPV6-ICMP-MIB.mib
boardfarm3/configs/mibs/IPV6-MIB.mib
boardfarm3/configs/mibs/IPV6-TC.mib.txt
boardfarm3/configs/mibs/IPV6-TCP-MIB.mib
boardfarm3/configs/mibs/IPV6-UDP-MIB.mib
boardfarm3/configs/mibs/RFC-1212-MIB.txt
boardfarm3/configs/mibs/RFC1155-SMI.mib
boardfarm3/configs/mibs/RFC1271-MIB.mib
boardfarm3/configs/mibs/RMON-MIB.mib
boardfarm3/configs/mibs/SNMP-COMMUNITY-MIB.mib
boardfarm3/configs/mibs/SNMP-FRAMEWORK-MIB.mib
boardfarm3/configs/mibs/SNMP-MPD-MIB.mib
boardfarm3/configs/mibs/SNMP-NOTIFICATION-MIB.mib
boardfarm3/configs/mibs/SNMP-PROXY-MIB.mib
boardfarm3/configs/mibs/SNMP-TARGET-MIB.mib
boardfarm3/configs/mibs/SNMP-USER-BASED-SM-MIB.mib
boardfarm3/configs/mibs/SNMP-USM-DH-OBJECTS-MIB.mib
boardfarm3/configs/mibs/SNMP-VIEW-BASED-ACM-MIB.mib
boardfarm3/configs/mibs/SNMPv2-CONF.txt
boardfarm3/configs/mibs/SNMPv2-MIB.txt
boardfarm3/configs/mibs/SNMPv2-SMI.txt
boardfarm3/configs/mibs/SNMPv2-TC.txt
boardfarm3-1.0.1.dist-info/entry_points.txt
boardfarm3-1.0.1.dist-info/licenses/LICENSE
boardfarm3-1.0.1.dist-info/WHEEL
boardfarm3-1.0.1.dist-info/METADATA
boardfarm3-1.0.1.dist-info/RECORD
