Metadata-Version: 2.4
Name: boardfarm3
Version: 1.0.1
Summary: Automated testing of network devices.
Author-email: Various <t&iconnectivityboardfarm@libertyglobal.com>
Requires-Python: >=3.9
Classifier: Intended Audience :: Developers
Classifier: Intended Audience :: Information Technology
Classifier: Intended Audience :: Telecommunications Industry
Classifier: License :: OSI Approved :: BSD License
Classifier: Topic :: Software Development :: Quality Assurance
Classifier: Topic :: Software Development :: Testing
Classifier: Topic :: Software Development :: Testing :: Acceptance
Classifier: Operating System :: POSIX :: Linux
Classifier: Topic :: Software Development :: Embedded Systems
Classifier: Programming Language :: Python :: 3.9
Classifier: Programming Language :: Python :: 3.10
Classifier: Programming Language :: Python :: 3.11
Classifier: Programming Language :: Python :: 3.12
Classifier: Programming Language :: Python :: 3.13
Classifier: Typing :: Typed
License-File: LICENSE
Requires-Dist: beautifulsoup4
Requires-Dist: httpx
Requires-Dist: importlib-metadata
Requires-Dist: jc
Requires-Dist: jsonmerge
Requires-Dist: netaddr
Requires-Dist: pandas
Requires-Dist: pexpect>=4.9
Requires-Dist: pluggy>=1.0.0
Requires-Dist: ptipython
Requires-Dist: pysmi
Requires-Dist: pytest
Requires-Dist: PyYAML
Requires-Dist: pyasn1==0.6.0
Requires-Dist: pysnmp-lextudio>=6,<6.1.2
Requires-Dist: requests
Requires-Dist: rich
Requires-Dist: kafka-python-ng
Requires-Dist: termcolor
Requires-Dist: selenium<4.15.0
Requires-Dist: xmltodict
Requires-Dist: debtcollector
Requires-Dist: scikit-image
Requires-Dist: opencv-python
Requires-Dist: flake8 ; extra == "dev"
Requires-Dist: flake8-bugbear ; extra == "dev"
Requires-Dist: flake8-builtins ; extra == "dev"
Requires-Dist: flake8-comprehensions ; extra == "dev"
Requires-Dist: flake8-docstrings ; extra == "dev"
Requires-Dist: flake8-rst ; extra == "dev"
Requires-Dist: flake8-rst-docstrings ; extra == "dev"
Requires-Dist: darglint2==v1.8.2 ; extra == "dev"
Requires-Dist: mypy>=1.3 ; extra == "dev"
Requires-Dist: nox ; extra == "dev"
Requires-Dist: pandas-stubs ; extra == "dev"
Requires-Dist: pre-commit ; extra == "dev"
Requires-Dist: pylint ; extra == "dev"
Requires-Dist: pylint-per-file-ignores ; extra == "dev"
Requires-Dist: ruff==v0.11.5 ; extra == "dev"
Requires-Dist: types-ipaddress ; extra == "dev"
Requires-Dist: types-PyYAML ; extra == "dev"
Requires-Dist: types-requests ; extra == "dev"
Requires-Dist: sphinx ; extra == "doc"
Requires-Dist: mkdocs ; extra == "doc"
Requires-Dist: mkdocs-material ; extra == "doc"
Requires-Dist: boardfarm3-docsis>=1.0.0 ; extra == "docsis"
Requires-Dist: pytest-boardfarm3>=1.0.0 ; extra == "pytest"
Requires-Dist: pytest-cov ; extra == "test"
Requires-Dist: pytest-mock ; extra == "test"
Requires-Dist: pytest-randomly ; extra == "test"
Project-URL: Documentation, https://ketantewari.github.io/boardfarm/
Project-URL: Source, https://github.com/lgirdk/boardfarm
Provides-Extra: dev
Provides-Extra: doc
Provides-Extra: docsis
Provides-Extra: pytest
Provides-Extra: test
